dns_client/__init__.py
dns_client/__main__.py
dns_client/client.py
dns_client/errors.py
dns_client/log.py
dns_client/protocol.py
dns_client/utils.py
dns_client/adapters/requests.py
dns_client-0.2.4.dist-info/LICENSE
dns_client-0.2.4.dist-info/METADATA
dns_client-0.2.4.dist-info/WHEEL
dns_client-0.2.4.dist-info/top_level.txt
dns_client-0.2.4.dist-info/RECORD
