Metadata-Version: 2.1
Name: dns-client
Version: 0.2.4
Author: Sergey M
License: FUCK LICENSE
Project-URL: Repository, https://github.com/s3rgeym/python-dns-client.git
Classifier: Topic :: Internet
Requires-Python: >=3.11.7
License-File: LICENSE
Provides-Extra: dev
Requires-Dist: black ; extra == 'dev'
Requires-Dist: pylint ; extra == 'dev'
Provides-Extra: requests
Requires-Dist: requests ; extra == 'requests'
Requires-Dist: cchardet ; extra == 'requests'
Provides-Extra: test
Requires-Dist: pytest ; extra == 'test'
